ez_qt/__init__.py
ez_qt/app_colors.py
ez_qt/combo_box.py
ez_qt/constants.py
ez_qt/general.py
ez_qt/list_widget.py
ez_qt/tree_widget.py
ez_qt-2.0.0.dist-info/LICENSE
ez_qt-2.0.0.dist-info/METADATA
ez_qt-2.0.0.dist-info/WHEEL
ez_qt-2.0.0.dist-info/top_level.txt
ez_qt-2.0.0.dist-info/RECORD
