Metadata-Version: 2.1
Name: ez_qt
Version: 2.0.0
Summary: Helper functions and classes to work with PySide6/PyQt5
Home-page: https://www.github.com/nielsvaes/ez_qt
Author: Niels Vaes
Author-email: nielsvaes@gmail.com
License: MIT
License-File: LICENSE
